pthflops/__init__.py
pthflops/ops_fx.py
pthflops/ops_jit.py
pthflops/utils.py
pthflops-0.4.2.dist-info/LICENSE
pthflops-0.4.2.dist-info/METADATA
pthflops-0.4.2.dist-info/WHEEL
pthflops-0.4.2.dist-info/top_level.txt
pthflops-0.4.2.dist-info/zip-safe
pthflops-0.4.2.dist-info/RECORD
